attention/__init__.py
attention/attention.py
attention-5.0.0.dist-info/LICENSE
attention-5.0.0.dist-info/METADATA
attention-5.0.0.dist-info/WHEEL
attention-5.0.0.dist-info/top_level.txt
attention-5.0.0.dist-info/RECORD
