Metadata-Version: 2.1
Name: attention
Version: 5.0.0
Summary: Keras Attention Layer
Author: Philippe Remy
License: Apache 2.0
License-File: LICENSE
Requires-Dist: numpy (>=1.18.1)
Requires-Dist: tensorflow (>=2.1)
